impick/__init__.py
impick/__version__.py
impick/py.typed
impick/server.py
impick/html/completed.html
impick/html/index.html
impick-0.1.2.dist-info/LICENSE
impick-0.1.2.dist-info/METADATA
impick-0.1.2.dist-info/WHEEL
impick-0.1.2.dist-info/entry_points.txt
impick-0.1.2.dist-info/top_level.txt
impick-0.1.2.dist-info/RECORD
