Metadata-Version: 2.1
Name: impick
Version: 0.1.2
Summary: ImPick - view and select a single image from a group using the web-GUI
Home-page: https://github.com/rilshok/impick
Author: Vladislav A. Proskurov
Author-email: rilshok@pm.me
License: MIT
Classifier: Programming Language :: Python :: 3.7
Classifier: License :: OSI Approved :: MIT License
Classifier: Operating System :: OS Independent
Classifier: Development Status :: 1 - Planning
Requires-Python: >=3.7
License-File: LICENSE
Requires-Dist: argcomplete
Requires-Dist: fastapi
Requires-Dist: jinja2
Requires-Dist: pandas
Requires-Dist: pytest
Requires-Dist: python-multipart
Requires-Dist: uvicorn
